liteapi/APIModel.py
liteapi/BaseAPIRequest.py
liteapi/__init__.py
liteapi/_internals.py
liteapi/error_no.py
liteapi/exception.py
liteapi/http_request.py
liteapi/http_response.py
liteapi/liteapi.py
liteapi/docs/__init__.py
liteapi/docs/annotate.py
liteapi/docs/docs.py
liteapi/security/__init__.py
liteapi/security/base_auth.py
liteapi/security/basic_auth.py
liteapi/security/digest_auth.py
liteapi/security/exception.py
liteapi/security/oauth2_auth.py
liteapi/verifiers/__init__.py
liteapi/verifiers/exception.py
liteapi/verifiers/verifiers.py
liteapi-0.5.3.dist-info/LICENSE
liteapi-0.5.3.dist-info/METADATA
liteapi-0.5.3.dist-info/WHEEL
liteapi-0.5.3.dist-info/top_level.txt
liteapi-0.5.3.dist-info/RECORD
